tf2_bfgs/__init__.py
tf2_bfgs/bfgs.py
tf2_bfgs-0.1.0.dist-info/LICENSE
tf2_bfgs-0.1.0.dist-info/METADATA
tf2_bfgs-0.1.0.dist-info/WHEEL
tf2_bfgs-0.1.0.dist-info/RECORD
