Metadata-Version: 2.1
Name: tf2-bfgs
Version: 0.1.0
Summary: Wrapper to train a tf.Module or tf.keras.Model using (L)BFGS optimizer from Tensorflow Probability
Author: Pi-Yueh Chuang
Author-email: pychuang@gwu.edu
Requires-Python: >=3.12
Classifier: Programming Language :: Python :: 3
Classifier: Programming Language :: Python :: 3.12
Requires-Dist: keras (>=3.0)
Requires-Dist: numpy (>=1.17)
Requires-Dist: tensorflow (>=2.12)
Requires-Dist: tensorflow-intel (>=2.12) ; sys_platform == "win32"
Requires-Dist: tensorflow-probability (>=0.24)
Requires-Dist: tf-keras (>=2.16.0)
